llmdatacleaner/__init__.py
llmdatacleaner/_api_validation.py
llmdatacleaner/openai_cleaner.py
llmdatacleaner/_utils/__init__.py
llmdatacleaner/_utils/logger.py
llmdatacleaner/_utils/settings.py
starai_llmdatacleaner-0.1.0.dist-info/METADATA
starai_llmdatacleaner-0.1.0.dist-info/WHEEL
starai_llmdatacleaner-0.1.0.dist-info/RECORD
