Metadata-Version: 2.4
Name: starai-llmdatacleaner
Version: 0.1.0
Summary: use llm to clean data for start ai
Requires-Python: >=3.10
Requires-Dist: openai>=1.74.0
Requires-Dist: pydantic-settings>=2.8.1
